fmtool/__init__.py
fmtool/filemanager.py
fmtool/version.py
fmtool-1.0.0.dist-info/licenses/LICENSE
fmtool-1.0.0.dist-info/METADATA
fmtool-1.0.0.dist-info/WHEEL
fmtool-1.0.0.dist-info/top_level.txt
fmtool-1.0.0.dist-info/RECORD
