Metadata-Version: 2.4
Name: fmtool
Version: 1.0.0
Summary: Cross-platform Python file manager
Author: Abbas Bachari
Author-email: Abbas Bachari <abbas-bachari@hotmail.com>
License-Expression: MIT
Classifier: Programming Language :: Python :: 3
Classifier: Operating System :: OS Independent
Requires-Python: >=3.8
License-File: LICENSE
Dynamic: author
Dynamic: license-file
Dynamic: requires-python
